<?xml version="1.0" encoding="UTF-8"?>
<dialog_box>
    <title>
        <text lang="en"> Combine NetCDF Data </text>
    </title>
    <widget>
        <button id="1">
            <text lang="en"> Set Date-Time Range </text>
        </button>
        <label id="1">
            <text lang="en"> Time step </text>
        </label>
        <label id="2">
            <text lang="en"> Directory containing the NetCDF files </text>
        </label>
        <label id="3">
            <text lang="en"> File to save the combined NetCDF files </text>
        </label>
    </widget>
    <message>
        <content id="1">
            <text lang="en"> Combine NetCDF data ................. </text>
        </content>
        <content id="2">
            <text lang="en"> Combining NetCDF data finished successfully </text>
        </content>
        <content id="3">
            <text lang="en"> Combining NetCDF data failed </text>
        </content>
        <content id="4">
            <text lang="en"> No NetCDF files found </text>
        </content>
        <content id="5">
            <text lang="en"> Unable to open the NetCDF sample </text>
        </content>
    </message>
</dialog_box>